{
  "generated_at": "2026-06-30T09:57:27.349445+00:00",
  "ports": {
    "Miami": {
      "tempF": 79,
      "tempC": 26.0,
      "condition": "Thunderstorm",
      "wmo": 95,
      "windKt": 4,
      "windDir": 350
    },
    "Key West": {
      "tempF": 83,
      "tempC": 28.3,
      "condition": "Thunderstorm",
      "wmo": 95,
      "windKt": 6,
      "windDir": 104
    },
    "Nassau": {
      "tempF": 76,
      "tempC": 24.2,
      "condition": "Sunny",
      "wmo": 0,
      "windKt": 4,
      "windDir": 61
    },
    "Bimini": {
      "tempF": 84,
      "tempC": 28.9,
      "condition": "Thunderstorm",
      "wmo": 95,
      "windKt": 4,
      "windDir": 93
    },
    "Freeport": {
      "tempF": 76,
      "tempC": 24.2,
      "condition": "Sunny",
      "wmo": 0,
      "windKt": 1,
      "windDir": 34
    },
    "Berry Islands": {
      "tempF": 83,
      "tempC": 28.1,
      "condition": "Sunny",
      "wmo": 0,
      "windKt": 6,
      "windDir": 94
    },
    "San Juan": {
      "tempF": 79,
      "tempC": 26.2,
      "condition": "Sunny",
      "wmo": 0,
      "windKt": 4,
      "windDir": 128
    },
    "St. Thomas": {
      "tempF": 82,
      "tempC": 27.5,
      "condition": "Mostly Clear",
      "wmo": 1,
      "windKt": 17,
      "windDir": 100
    },
    "St. Croix": {
      "tempF": 80,
      "tempC": 26.5,
      "condition": "Mostly Clear",
      "wmo": 1,
      "windKt": 12,
      "windDir": 96
    },
    "St. Kitts": {
      "tempF": 79,
      "tempC": 26.1,
      "condition": "Light Drizzle",
      "wmo": 51,
      "windKt": 12,
      "windDir": 95
    },
    "Antigua": {
      "tempF": 79,
      "tempC": 26.2,
      "condition": "Mostly Clear",
      "wmo": 1,
      "windKt": 12,
      "windDir": 94
    },
    "Barbados": {
      "tempF": 78,
      "tempC": 25.4,
      "condition": "Partly Cloudy",
      "wmo": 2,
      "windKt": 10,
      "windDir": 73
    },
    "St. Lucia": {
      "tempF": 74,
      "tempC": 23.1,
      "condition": "Partly Cloudy",
      "wmo": 2,
      "windKt": 8,
      "windDir": 89
    },
    "Martinique": {
      "tempF": 76,
      "tempC": 24.7,
      "condition": "Partly Cloudy",
      "wmo": 2,
      "windKt": 7,
      "windDir": 82
    },
    "St. Maarten": {
      "tempF": 80,
      "tempC": 26.8,
      "condition": "Sunny",
      "wmo": 0,
      "windKt": 17,
      "windDir": 90
    },
    "Turks & Caicos": {
      "tempF": 81,
      "tempC": 27.2,
      "condition": "Thunderstorm",
      "wmo": 95,
      "windKt": 11,
      "windDir": 103
    },
    "Cozumel": {
      "tempF": 79,
      "tempC": 26.1,
      "condition": "Thunderstorm",
      "wmo": 95,
      "windKt": 2,
      "windDir": 56
    },
    "Costa Maya": {
      "tempF": 83,
      "tempC": 28.4,
      "condition": "Thunderstorm",
      "wmo": 95,
      "windKt": 7,
      "windDir": 103
    },
    "Roatan": {
      "tempF": 80,
      "tempC": 26.9,
      "condition": "Partly Cloudy",
      "wmo": 2,
      "windKt": 17,
      "windDir": 96
    },
    "Belize City": {
      "tempF": 77,
      "tempC": 25.0,
      "condition": "Overcast",
      "wmo": 3,
      "windKt": 5,
      "windDir": 95
    },
    "Grand Cayman": {
      "tempF": 83,
      "tempC": 28.2,
      "condition": "Thunderstorm",
      "wmo": 95,
      "windKt": 8,
      "windDir": 53
    },
    "Ocho Rios": {
      "tempF": 80,
      "tempC": 26.4,
      "condition": "Mostly Clear",
      "wmo": 1,
      "windKt": 4,
      "windDir": 131
    },
    "Aruba": {
      "tempF": 81,
      "tempC": 27.0,
      "condition": "Overcast",
      "wmo": 3,
      "windKt": 16,
      "windDir": 99
    },
    "Curacao": {
      "tempF": 80,
      "tempC": 26.6,
      "condition": "Mostly Clear",
      "wmo": 1,
      "windKt": 13,
      "windDir": 105
    },
    "Cartagena": {
      "tempF": 81,
      "tempC": 27.2,
      "condition": "Overcast",
      "wmo": 3,
      "windKt": 2,
      "windDir": 109
    },
    "Barcelona": {
      "tempF": 89,
      "tempC": 31.7,
      "condition": "Sunny",
      "wmo": 0,
      "windKt": 3,
      "windDir": 187
    },
    "Valencia": {
      "tempF": 89,
      "tempC": 31.9,
      "condition": "Sunny",
      "wmo": 0,
      "windKt": 4,
      "windDir": 110
    },
    "Palma": {
      "tempF": 87,
      "tempC": 30.3,
      "condition": "Sunny",
      "wmo": 0,
      "windKt": 4,
      "windDir": 178
    },
    "Ibiza": {
      "tempF": 87,
      "tempC": 30.8,
      "condition": "Sunny",
      "wmo": 0,
      "windKt": 6,
      "windDir": 110
    },
    "Malaga": {
      "tempF": 85,
      "tempC": 29.5,
      "condition": "Sunny",
      "wmo": 0,
      "windKt": 5,
      "windDir": 176
    },
    "Cadiz": {
      "tempF": 83,
      "tempC": 28.4,
      "condition": "Sunny",
      "wmo": 0,
      "windKt": 3,
      "windDir": 42
    },
    "Lisbon": {
      "tempF": 75,
      "tempC": 24.1,
      "condition": "Sunny",
      "wmo": 0,
      "windKt": 6,
      "windDir": 343
    },
    "Marseille": {
      "tempF": 89,
      "tempC": 31.6,
      "condition": "Sunny",
      "wmo": 0,
      "windKt": 7,
      "windDir": 268
    },
    "Nice": {
      "tempF": 90,
      "tempC": 32.1,
      "condition": "Partly Cloudy",
      "wmo": 2,
      "windKt": 5,
      "windDir": 160
    },
    "Monaco": {
      "tempF": 87,
      "tempC": 30.5,
      "condition": "Mostly Clear",
      "wmo": 1,
      "windKt": 4,
      "windDir": 162
    },
    "Genoa": {
      "tempF": 87,
      "tempC": 30.3,
      "condition": "Overcast",
      "wmo": 3,
      "windKt": 2,
      "windDir": 175
    },
    "La Spezia": {
      "tempF": 89,
      "tempC": 31.5,
      "condition": "Overcast",
      "wmo": 3,
      "windKt": 2,
      "windDir": 347
    },
    "Livorno": {
      "tempF": 88,
      "tempC": 31.1,
      "condition": "Mostly Clear",
      "wmo": 1,
      "windKt": 2,
      "windDir": 275
    },
    "Civitavecchia": {
      "tempF": 90,
      "tempC": 32.5,
      "condition": "Mostly Clear",
      "wmo": 1,
      "windKt": 6,
      "windDir": 278
    },
    "Naples": {
      "tempF": 93,
      "tempC": 34.1,
      "condition": "Sunny",
      "wmo": 0,
      "windKt": 4,
      "windDir": 192
    },
    "Sardinia": {
      "tempF": 91,
      "tempC": 32.8,
      "condition": "Mostly Clear",
      "wmo": 1,
      "windKt": 4,
      "windDir": 189
    },
    "Corsica": {
      "tempF": 77,
      "tempC": 24.9,
      "condition": "Overcast",
      "wmo": 3,
      "windKt": 3,
      "windDir": 278
    },
    "Split": {
      "tempF": 94,
      "tempC": 34.6,
      "condition": "Sunny",
      "wmo": 0,
      "windKt": 5,
      "windDir": 230
    },
    "Dubrovnik": {
      "tempF": 92,
      "tempC": 33.2,
      "condition": "Sunny",
      "wmo": 0,
      "windKt": 4,
      "windDir": 211
    },
    "Venice": {
      "tempF": 90,
      "tempC": 32.2,
      "condition": "Partly Cloudy",
      "wmo": 2,
      "windKt": 3,
      "windDir": 117
    },
    "Athens": {
      "tempF": 96,
      "tempC": 35.4,
      "condition": "Partly Cloudy",
      "wmo": 2,
      "windKt": 7,
      "windDir": 22
    },
    "Santorini": {
      "tempF": 82,
      "tempC": 27.9,
      "condition": "Sunny",
      "wmo": 0,
      "windKt": 8,
      "windDir": 275
    },
    "Mykonos": {
      "tempF": 81,
      "tempC": 27.4,
      "condition": "Mostly Clear",
      "wmo": 1,
      "windKt": 8,
      "windDir": 347
    },
    "Rhodes": {
      "tempF": 87,
      "tempC": 30.3,
      "condition": "Sunny",
      "wmo": 0,
      "windKt": 13,
      "windDir": 286
    },
    "Corfu": {
      "tempF": 95,
      "tempC": 35.1,
      "condition": "Mostly Clear",
      "wmo": 1,
      "windKt": 4,
      "windDir": 351
    },
    "Istanbul": {
      "tempF": 85,
      "tempC": 29.5,
      "condition": "Sunny",
      "wmo": 0,
      "windKt": 11,
      "windDir": 29
    },
    "Izmir": {
      "tempF": 96,
      "tempC": 35.4,
      "condition": "Sunny",
      "wmo": 0,
      "windKt": 7,
      "windDir": 270
    },
    "Cyprus": {
      "tempF": 92,
      "tempC": 33.5,
      "condition": "Sunny",
      "wmo": 0,
      "windKt": 8,
      "windDir": 177
    },
    "Haifa": {
      "tempF": 85,
      "tempC": 29.3,
      "condition": "Partly Cloudy",
      "wmo": 2,
      "windKt": 10,
      "windDir": 256
    },
    "Alexandria": {
      "tempF": 85,
      "tempC": 29.4,
      "condition": "Mostly Clear",
      "wmo": 1,
      "windKt": 8,
      "windDir": 316
    },
    "Bonaire": {
      "tempF": 79,
      "tempC": 26.3,
      "condition": "Mostly Clear",
      "wmo": 1,
      "windKt": 15,
      "windDir": 105
    },
    "Dominica": {
      "tempF": 77,
      "tempC": 24.9,
      "condition": "Light Drizzle",
      "wmo": 51,
      "windKt": 9,
      "windDir": 77
    },
    "Falmouth": {
      "tempF": 80,
      "tempC": 26.4,
      "condition": "Sunny",
      "wmo": 0,
      "windKt": 5,
      "windDir": 110
    },
    "La Romana": {
      "tempF": 79,
      "tempC": 26.0,
      "condition": "Mostly Clear",
      "wmo": 1,
      "windKt": 7,
      "windDir": 103
    },
    "Puerto Plata": {
      "tempF": 77,
      "tempC": 25.0,
      "condition": "Sunny",
      "wmo": 0,
      "windKt": 2,
      "windDir": 155
    },
    "Samana": {
      "tempF": 75,
      "tempC": 23.8,
      "condition": "Thunderstorm",
      "wmo": 95,
      "windKt": 0,
      "windDir": 180
    },
    "Santo Domingo": {
      "tempF": 75,
      "tempC": 24.0,
      "condition": "Mostly Clear",
      "wmo": 1,
      "windKt": 3,
      "windDir": 12
    },
    "Ensenada": {
      "tempF": 62,
      "tempC": 16.4,
      "condition": "Overcast",
      "wmo": 3,
      "windKt": 1,
      "windDir": 360
    },
    "Cabo San Lucas": {
      "tempF": 82,
      "tempC": 27.6,
      "condition": "Overcast",
      "wmo": 3,
      "windKt": 8,
      "windDir": 313
    },
    "Mazatlan": {
      "tempF": 83,
      "tempC": 28.5,
      "condition": "Thunderstorm",
      "wmo": 95,
      "windKt": 2,
      "windDir": 22
    },
    "Puerto Vallarta": {
      "tempF": 80,
      "tempC": 26.6,
      "condition": "Partly Cloudy",
      "wmo": 2,
      "windKt": 3,
      "windDir": 45
    },
    "Manzanillo": {
      "tempF": 83,
      "tempC": 28.4,
      "condition": "Sunny",
      "wmo": 0,
      "windKt": 3,
      "windDir": 37
    },
    "Huatulco": {
      "tempF": 79,
      "tempC": 26.3,
      "condition": "Sunny",
      "wmo": 0,
      "windKt": 2,
      "windDir": 347
    }
  }
}