{
  "generated_at": "2026-05-13T09:15:44.955604+00:00",
  "ports": {
    "Miami": {
      "tempF": 76,
      "tempC": 24.3,
      "condition": "Partly Cloudy",
      "wmo": 2,
      "windKt": 4,
      "windDir": 162
    },
    "Key West": {
      "tempF": 78,
      "tempC": 25.7,
      "condition": "Overcast",
      "wmo": 3,
      "windKt": 4,
      "windDir": 307
    },
    "Nassau": {
      "tempF": 78,
      "tempC": 25.7,
      "condition": "Overcast",
      "wmo": 3,
      "windKt": 8,
      "windDir": 154
    },
    "Bimini": {
      "tempF": 78,
      "tempC": 25.8,
      "condition": "Mostly Clear",
      "wmo": 1,
      "windKt": 5,
      "windDir": 142
    },
    "Freeport": {
      "tempF": 74,
      "tempC": 23.4,
      "condition": "Overcast",
      "wmo": 3,
      "windKt": 8,
      "windDir": 82
    },
    "Berry Islands": {
      "tempF": 81,
      "tempC": 27.4,
      "condition": "Overcast",
      "wmo": 3,
      "windKt": 16,
      "windDir": 163
    },
    "San Juan": {
      "tempF": 76,
      "tempC": 24.3,
      "condition": "Sunny",
      "wmo": 0,
      "windKt": 5,
      "windDir": 139
    },
    "St. Thomas": {
      "tempF": 80,
      "tempC": 26.7,
      "condition": "Sunny",
      "wmo": 0,
      "windKt": 17,
      "windDir": 107
    },
    "St. Croix": {
      "tempF": 78,
      "tempC": 25.7,
      "condition": "Sunny",
      "wmo": 0,
      "windKt": 12,
      "windDir": 104
    },
    "St. Kitts": {
      "tempF": 79,
      "tempC": 26.2,
      "condition": "Sunny",
      "wmo": 0,
      "windKt": 11,
      "windDir": 98
    },
    "Antigua": {
      "tempF": 78,
      "tempC": 25.8,
      "condition": "Mostly Clear",
      "wmo": 1,
      "windKt": 10,
      "windDir": 100
    },
    "Barbados": {
      "tempF": 78,
      "tempC": 25.8,
      "condition": "Sunny",
      "wmo": 0,
      "windKt": 10,
      "windDir": 85
    },
    "St. Lucia": {
      "tempF": 73,
      "tempC": 22.6,
      "condition": "Mostly Clear",
      "wmo": 1,
      "windKt": 7,
      "windDir": 85
    },
    "Martinique": {
      "tempF": 73,
      "tempC": 22.7,
      "condition": "Mostly Clear",
      "wmo": 1,
      "windKt": 7,
      "windDir": 67
    },
    "St. Maarten": {
      "tempF": 79,
      "tempC": 26.2,
      "condition": "Sunny",
      "wmo": 0,
      "windKt": 17,
      "windDir": 105
    },
    "Turks & Caicos": {
      "tempF": 81,
      "tempC": 27.3,
      "condition": "Overcast",
      "wmo": 3,
      "windKt": 18,
      "windDir": 129
    },
    "Cozumel": {
      "tempF": 77,
      "tempC": 25.0,
      "condition": "Mostly Clear",
      "wmo": 1,
      "windKt": 2,
      "windDir": 175
    },
    "Costa Maya": {
      "tempF": 80,
      "tempC": 26.6,
      "condition": "Sunny",
      "wmo": 0,
      "windKt": 5,
      "windDir": 148
    },
    "Roatan": {
      "tempF": 81,
      "tempC": 27.2,
      "condition": "Mostly Clear",
      "wmo": 1,
      "windKt": 11,
      "windDir": 94
    },
    "Belize City": {
      "tempF": 72,
      "tempC": 22.5,
      "condition": "Sunny",
      "wmo": 0,
      "windKt": 2,
      "windDir": 137
    },
    "Grand Cayman": {
      "tempF": 79,
      "tempC": 25.9,
      "condition": "Overcast",
      "wmo": 3,
      "windKt": 0,
      "windDir": 79
    },
    "Ocho Rios": {
      "tempF": 73,
      "tempC": 22.7,
      "condition": "Mostly Clear",
      "wmo": 1,
      "windKt": 4,
      "windDir": 199
    },
    "Aruba": {
      "tempF": 80,
      "tempC": 26.9,
      "condition": "Overcast",
      "wmo": 3,
      "windKt": 19,
      "windDir": 98
    },
    "Curacao": {
      "tempF": 80,
      "tempC": 26.5,
      "condition": "Overcast",
      "wmo": 3,
      "windKt": 13,
      "windDir": 96
    },
    "Cartagena": {
      "tempF": 80,
      "tempC": 26.7,
      "condition": "Partly Cloudy",
      "wmo": 2,
      "windKt": 4,
      "windDir": 51
    },
    "Barcelona": {
      "tempF": 64,
      "tempC": 17.5,
      "condition": "Sunny",
      "wmo": 0,
      "windKt": 4,
      "windDir": 285
    },
    "Valencia": {
      "tempF": 72,
      "tempC": 22.4,
      "condition": "Mostly Clear",
      "wmo": 1,
      "windKt": 8,
      "windDir": 293
    },
    "Palma": {
      "tempF": 67,
      "tempC": 19.2,
      "condition": "Mostly Clear",
      "wmo": 1,
      "windKt": 11,
      "windDir": 333
    },
    "Ibiza": {
      "tempF": 69,
      "tempC": 20.6,
      "condition": "Mostly Clear",
      "wmo": 1,
      "windKt": 9,
      "windDir": 310
    },
    "Malaga": {
      "tempF": 71,
      "tempC": 21.5,
      "condition": "Sunny",
      "wmo": 0,
      "windKt": 8,
      "windDir": 316
    },
    "Cadiz": {
      "tempF": 64,
      "tempC": 17.5,
      "condition": "Mostly Clear",
      "wmo": 1,
      "windKt": 5,
      "windDir": 289
    },
    "Lisbon": {
      "tempF": 62,
      "tempC": 16.4,
      "condition": "Partly Cloudy",
      "wmo": 2,
      "windKt": 2,
      "windDir": 180
    },
    "Marseille": {
      "tempF": 64,
      "tempC": 17.5,
      "condition": "Overcast",
      "wmo": 3,
      "windKt": 15,
      "windDir": 318
    },
    "Nice": {
      "tempF": 68,
      "tempC": 20.0,
      "condition": "Partly Cloudy",
      "wmo": 2,
      "windKt": 4,
      "windDir": 183
    },
    "Monaco": {
      "tempF": 65,
      "tempC": 18.6,
      "condition": "Partly Cloudy",
      "wmo": 2,
      "windKt": 4,
      "windDir": 193
    },
    "Genoa": {
      "tempF": 63,
      "tempC": 17.1,
      "condition": "Overcast",
      "wmo": 3,
      "windKt": 9,
      "windDir": 10
    },
    "La Spezia": {
      "tempF": 65,
      "tempC": 18.1,
      "condition": "Overcast",
      "wmo": 3,
      "windKt": 6,
      "windDir": 184
    },
    "Livorno": {
      "tempF": 63,
      "tempC": 17.1,
      "condition": "Rain Showers",
      "wmo": 80,
      "windKt": 5,
      "windDir": 327
    },
    "Civitavecchia": {
      "tempF": 64,
      "tempC": 17.9,
      "condition": "Rain Showers",
      "wmo": 80,
      "windKt": 6,
      "windDir": 191
    },
    "Naples": {
      "tempF": 64,
      "tempC": 17.7,
      "condition": "Thunderstorm",
      "wmo": 95,
      "windKt": 7,
      "windDir": 246
    },
    "Sardinia": {
      "tempF": 68,
      "tempC": 20.1,
      "condition": "Partly Cloudy",
      "wmo": 2,
      "windKt": 10,
      "windDir": 297
    },
    "Corsica": {
      "tempF": 48,
      "tempC": 8.9,
      "condition": "Overcast",
      "wmo": 3,
      "windKt": 6,
      "windDir": 281
    },
    "Split": {
      "tempF": 63,
      "tempC": 17.0,
      "condition": "Overcast",
      "wmo": 3,
      "windKt": 3,
      "windDir": 117
    },
    "Dubrovnik": {
      "tempF": 65,
      "tempC": 18.1,
      "condition": "Overcast",
      "wmo": 3,
      "windKt": 5,
      "windDir": 258
    },
    "Venice": {
      "tempF": 60,
      "tempC": 15.8,
      "condition": "Overcast",
      "wmo": 3,
      "windKt": 6,
      "windDir": 105
    },
    "Athens": {
      "tempF": 80,
      "tempC": 26.4,
      "condition": "Overcast",
      "wmo": 3,
      "windKt": 5,
      "windDir": 236
    },
    "Santorini": {
      "tempF": 71,
      "tempC": 21.8,
      "condition": "Overcast",
      "wmo": 3,
      "windKt": 8,
      "windDir": 263
    },
    "Mykonos": {
      "tempF": 73,
      "tempC": 22.6,
      "condition": "Mostly Clear",
      "wmo": 1,
      "windKt": 10,
      "windDir": 233
    },
    "Rhodes": {
      "tempF": 75,
      "tempC": 24.0,
      "condition": "Overcast",
      "wmo": 3,
      "windKt": 9,
      "windDir": 293
    },
    "Corfu": {
      "tempF": 70,
      "tempC": 21.1,
      "condition": "Overcast",
      "wmo": 3,
      "windKt": 4,
      "windDir": 103
    },
    "Istanbul": {
      "tempF": 71,
      "tempC": 21.4,
      "condition": "Overcast",
      "wmo": 3,
      "windKt": 7,
      "windDir": 233
    },
    "Izmir": {
      "tempF": 81,
      "tempC": 27.1,
      "condition": "Mostly Clear",
      "wmo": 1,
      "windKt": 6,
      "windDir": 211
    },
    "Cyprus": {
      "tempF": 78,
      "tempC": 25.6,
      "condition": "Mostly Clear",
      "wmo": 1,
      "windKt": 3,
      "windDir": 135
    },
    "Haifa": {
      "tempF": 75,
      "tempC": 24.1,
      "condition": "Mostly Clear",
      "wmo": 1,
      "windKt": 12,
      "windDir": 229
    },
    "Alexandria": {
      "tempF": 79,
      "tempC": 26.0,
      "condition": "Sunny",
      "wmo": 0,
      "windKt": 6,
      "windDir": 272
    },
    "Bonaire": {
      "tempF": 76,
      "tempC": 24.5,
      "condition": "Light Drizzle",
      "wmo": 51,
      "windKt": 12,
      "windDir": 104
    },
    "Dominica": {
      "tempF": 74,
      "tempC": 23.3,
      "condition": "Mostly Clear",
      "wmo": 1,
      "windKt": 9,
      "windDir": 65
    },
    "Falmouth": {
      "tempF": 73,
      "tempC": 22.6,
      "condition": "Partly Cloudy",
      "wmo": 2,
      "windKt": 3,
      "windDir": 185
    },
    "La Romana": {
      "tempF": 77,
      "tempC": 25.1,
      "condition": "Overcast",
      "wmo": 3,
      "windKt": 6,
      "windDir": 85
    },
    "Puerto Plata": {
      "tempF": 76,
      "tempC": 24.4,
      "condition": "Mostly Clear",
      "wmo": 1,
      "windKt": 6,
      "windDir": 121
    },
    "Samana": {
      "tempF": 74,
      "tempC": 23.4,
      "condition": "Overcast",
      "wmo": 3,
      "windKt": 2,
      "windDir": 144
    },
    "Santo Domingo": {
      "tempF": 74,
      "tempC": 23.2,
      "condition": "Overcast",
      "wmo": 3,
      "windKt": 3,
      "windDir": 325
    },
    "Ensenada": {
      "tempF": 62,
      "tempC": 16.6,
      "condition": "Overcast",
      "wmo": 3,
      "windKt": 2,
      "windDir": 194
    },
    "Cabo San Lucas": {
      "tempF": 83,
      "tempC": 28.1,
      "condition": "Sunny",
      "wmo": 0,
      "windKt": 0,
      "windDir": 112
    },
    "Mazatlan": {
      "tempF": 77,
      "tempC": 24.8,
      "condition": "Sunny",
      "wmo": 0,
      "windKt": 2,
      "windDir": 127
    },
    "Puerto Vallarta": {
      "tempF": 79,
      "tempC": 26.2,
      "condition": "Sunny",
      "wmo": 0,
      "windKt": 2,
      "windDir": 24
    },
    "Manzanillo": {
      "tempF": 80,
      "tempC": 26.4,
      "condition": "Mostly Clear",
      "wmo": 1,
      "windKt": 3,
      "windDir": 39
    },
    "Huatulco": {
      "tempF": 83,
      "tempC": 28.2,
      "condition": "Light Drizzle",
      "wmo": 51,
      "windKt": 2,
      "windDir": 72
    }
  }
}