{
  "generated_at": "2026-06-06T16:16:48.536184+00:00",
  "ports": {
    "Miami": {
      "tempF": 83,
      "tempC": 28.2,
      "condition": "Sunny",
      "wmo": 0,
      "windKt": 9,
      "windDir": 54
    },
    "Key West": {
      "tempF": 84,
      "tempC": 28.9,
      "condition": "Sunny",
      "wmo": 0,
      "windKt": 9,
      "windDir": 67
    },
    "Nassau": {
      "tempF": 84,
      "tempC": 28.8,
      "condition": "Mostly Clear",
      "wmo": 1,
      "windKt": 10,
      "windDir": 78
    },
    "Bimini": {
      "tempF": 80,
      "tempC": 26.7,
      "condition": "Sunny",
      "wmo": 0,
      "windKt": 14,
      "windDir": 59
    },
    "Freeport": {
      "tempF": 84,
      "tempC": 28.8,
      "condition": "Sunny",
      "wmo": 0,
      "windKt": 9,
      "windDir": 95
    },
    "Berry Islands": {
      "tempF": 79,
      "tempC": 26.3,
      "condition": "Sunny",
      "wmo": 0,
      "windKt": 14,
      "windDir": 65
    },
    "San Juan": {
      "tempF": 83,
      "tempC": 28.2,
      "condition": "Thunderstorm",
      "wmo": 95,
      "windKt": 13,
      "windDir": 66
    },
    "St. Thomas": {
      "tempF": 81,
      "tempC": 27.1,
      "condition": "Partly Cloudy",
      "wmo": 2,
      "windKt": 13,
      "windDir": 111
    },
    "St. Croix": {
      "tempF": 85,
      "tempC": 29.7,
      "condition": "Drizzle",
      "wmo": 53,
      "windKt": 10,
      "windDir": 110
    },
    "St. Kitts": {
      "tempF": 84,
      "tempC": 28.8,
      "condition": "Drizzle",
      "wmo": 53,
      "windKt": 12,
      "windDir": 96
    },
    "Antigua": {
      "tempF": 86,
      "tempC": 29.8,
      "condition": "Drizzle",
      "wmo": 53,
      "windKt": 14,
      "windDir": 102
    },
    "Barbados": {
      "tempF": 84,
      "tempC": 28.8,
      "condition": "Drizzle",
      "wmo": 53,
      "windKt": 14,
      "windDir": 98
    },
    "St. Lucia": {
      "tempF": 83,
      "tempC": 28.3,
      "condition": "Drizzle",
      "wmo": 53,
      "windKt": 9,
      "windDir": 97
    },
    "Martinique": {
      "tempF": 82,
      "tempC": 27.9,
      "condition": "Drizzle",
      "wmo": 53,
      "windKt": 10,
      "windDir": 92
    },
    "St. Maarten": {
      "tempF": 81,
      "tempC": 27.0,
      "condition": "Overcast",
      "wmo": 3,
      "windKt": 14,
      "windDir": 112
    },
    "Turks & Caicos": {
      "tempF": 82,
      "tempC": 27.6,
      "condition": "Overcast",
      "wmo": 3,
      "windKt": 13,
      "windDir": 133
    },
    "Cozumel": {
      "tempF": 85,
      "tempC": 29.3,
      "condition": "Heavy Drizzle",
      "wmo": 55,
      "windKt": 9,
      "windDir": 119
    },
    "Costa Maya": {
      "tempF": 86,
      "tempC": 29.8,
      "condition": "Overcast",
      "wmo": 3,
      "windKt": 8,
      "windDir": 108
    },
    "Roatan": {
      "tempF": 81,
      "tempC": 27.4,
      "condition": "Mostly Clear",
      "wmo": 1,
      "windKt": 15,
      "windDir": 94
    },
    "Belize City": {
      "tempF": 88,
      "tempC": 31.1,
      "condition": "Overcast",
      "wmo": 3,
      "windKt": 9,
      "windDir": 98
    },
    "Grand Cayman": {
      "tempF": 88,
      "tempC": 31.0,
      "condition": "Light Drizzle",
      "wmo": 51,
      "windKt": 10,
      "windDir": 82
    },
    "Ocho Rios": {
      "tempF": 85,
      "tempC": 29.4,
      "condition": "Drizzle",
      "wmo": 53,
      "windKt": 6,
      "windDir": 90
    },
    "Aruba": {
      "tempF": 86,
      "tempC": 30.2,
      "condition": "Overcast",
      "wmo": 3,
      "windKt": 17,
      "windDir": 106
    },
    "Curacao": {
      "tempF": 87,
      "tempC": 30.5,
      "condition": "Partly Cloudy",
      "wmo": 2,
      "windKt": 14,
      "windDir": 111
    },
    "Cartagena": {
      "tempF": 82,
      "tempC": 27.6,
      "condition": "Rain Showers",
      "wmo": 80,
      "windKt": 4,
      "windDir": 224
    },
    "Barcelona": {
      "tempF": 76,
      "tempC": 24.3,
      "condition": "Mostly Clear",
      "wmo": 1,
      "windKt": 6,
      "windDir": 190
    },
    "Valencia": {
      "tempF": 75,
      "tempC": 24.1,
      "condition": "Overcast",
      "wmo": 3,
      "windKt": 7,
      "windDir": 109
    },
    "Palma": {
      "tempF": 74,
      "tempC": 23.3,
      "condition": "Overcast",
      "wmo": 3,
      "windKt": 5,
      "windDir": 185
    },
    "Ibiza": {
      "tempF": 75,
      "tempC": 23.7,
      "condition": "Partly Cloudy",
      "wmo": 2,
      "windKt": 7,
      "windDir": 123
    },
    "Malaga": {
      "tempF": 78,
      "tempC": 25.5,
      "condition": "Overcast",
      "wmo": 3,
      "windKt": 5,
      "windDir": 159
    },
    "Cadiz": {
      "tempF": 72,
      "tempC": 22.2,
      "condition": "Mostly Clear",
      "wmo": 1,
      "windKt": 8,
      "windDir": 305
    },
    "Lisbon": {
      "tempF": 74,
      "tempC": 23.2,
      "condition": "Overcast",
      "wmo": 3,
      "windKt": 10,
      "windDir": 341
    },
    "Marseille": {
      "tempF": 71,
      "tempC": 21.6,
      "condition": "Overcast",
      "wmo": 3,
      "windKt": 4,
      "windDir": 254
    },
    "Nice": {
      "tempF": 74,
      "tempC": 23.6,
      "condition": "Sunny",
      "wmo": 0,
      "windKt": 4,
      "windDir": 108
    },
    "Monaco": {
      "tempF": 72,
      "tempC": 22.2,
      "condition": "Sunny",
      "wmo": 0,
      "windKt": 4,
      "windDir": 127
    },
    "Genoa": {
      "tempF": 72,
      "tempC": 22.5,
      "condition": "Mostly Clear",
      "wmo": 1,
      "windKt": 4,
      "windDir": 208
    },
    "La Spezia": {
      "tempF": 74,
      "tempC": 23.4,
      "condition": "Mostly Clear",
      "wmo": 1,
      "windKt": 4,
      "windDir": 236
    },
    "Livorno": {
      "tempF": 71,
      "tempC": 21.8,
      "condition": "Partly Cloudy",
      "wmo": 2,
      "windKt": 9,
      "windDir": 265
    },
    "Civitavecchia": {
      "tempF": 75,
      "tempC": 23.9,
      "condition": "Mostly Clear",
      "wmo": 1,
      "windKt": 7,
      "windDir": 286
    },
    "Naples": {
      "tempF": 79,
      "tempC": 26.3,
      "condition": "Sunny",
      "wmo": 0,
      "windKt": 7,
      "windDir": 264
    },
    "Sardinia": {
      "tempF": 76,
      "tempC": 24.5,
      "condition": "Sunny",
      "wmo": 0,
      "windKt": 8,
      "windDir": 162
    },
    "Corsica": {
      "tempF": 61,
      "tempC": 16.1,
      "condition": "Sunny",
      "wmo": 0,
      "windKt": 6,
      "windDir": 288
    },
    "Split": {
      "tempF": 77,
      "tempC": 24.8,
      "condition": "Partly Cloudy",
      "wmo": 2,
      "windKt": 3,
      "windDir": 247
    },
    "Dubrovnik": {
      "tempF": 76,
      "tempC": 24.7,
      "condition": "Overcast",
      "wmo": 3,
      "windKt": 2,
      "windDir": 221
    },
    "Venice": {
      "tempF": 74,
      "tempC": 23.4,
      "condition": "Sunny",
      "wmo": 0,
      "windKt": 6,
      "windDir": 153
    },
    "Athens": {
      "tempF": 80,
      "tempC": 26.9,
      "condition": "Sunny",
      "wmo": 0,
      "windKt": 4,
      "windDir": 187
    },
    "Santorini": {
      "tempF": 75,
      "tempC": 23.9,
      "condition": "Sunny",
      "wmo": 0,
      "windKt": 5,
      "windDir": 287
    },
    "Mykonos": {
      "tempF": 76,
      "tempC": 24.3,
      "condition": "Sunny",
      "wmo": 0,
      "windKt": 4,
      "windDir": 354
    },
    "Rhodes": {
      "tempF": 77,
      "tempC": 24.8,
      "condition": "Sunny",
      "wmo": 0,
      "windKt": 10,
      "windDir": 286
    },
    "Corfu": {
      "tempF": 78,
      "tempC": 25.5,
      "condition": "Mostly Clear",
      "wmo": 1,
      "windKt": 4,
      "windDir": 259
    },
    "Istanbul": {
      "tempF": 72,
      "tempC": 22.5,
      "condition": "Sunny",
      "wmo": 0,
      "windKt": 11,
      "windDir": 27
    },
    "Izmir": {
      "tempF": 84,
      "tempC": 29.0,
      "condition": "Sunny",
      "wmo": 0,
      "windKt": 7,
      "windDir": 273
    },
    "Cyprus": {
      "tempF": 82,
      "tempC": 27.7,
      "condition": "Sunny",
      "wmo": 0,
      "windKt": 11,
      "windDir": 340
    },
    "Haifa": {
      "tempF": 75,
      "tempC": 24.0,
      "condition": "Sunny",
      "wmo": 0,
      "windKt": 8,
      "windDir": 351
    },
    "Alexandria": {
      "tempF": 73,
      "tempC": 23.0,
      "condition": "Partly Cloudy",
      "wmo": 2,
      "windKt": 9,
      "windDir": 327
    },
    "Bonaire": {
      "tempF": 85,
      "tempC": 29.6,
      "condition": "Partly Cloudy",
      "wmo": 2,
      "windKt": 14,
      "windDir": 108
    },
    "Dominica": {
      "tempF": 83,
      "tempC": 28.4,
      "condition": "Light Drizzle",
      "wmo": 51,
      "windKt": 12,
      "windDir": 90
    },
    "Falmouth": {
      "tempF": 78,
      "tempC": 25.3,
      "condition": "Rain Showers",
      "wmo": 80,
      "windKt": 5,
      "windDir": 89
    },
    "La Romana": {
      "tempF": 84,
      "tempC": 28.9,
      "condition": "Light Drizzle",
      "wmo": 51,
      "windKt": 6,
      "windDir": 126
    },
    "Puerto Plata": {
      "tempF": 85,
      "tempC": 29.3,
      "condition": "Thunderstorm",
      "wmo": 95,
      "windKt": 8,
      "windDir": 55
    },
    "Samana": {
      "tempF": 84,
      "tempC": 28.8,
      "condition": "Rain Showers",
      "wmo": 80,
      "windKt": 6,
      "windDir": 121
    },
    "Santo Domingo": {
      "tempF": 83,
      "tempC": 28.5,
      "condition": "Light Drizzle",
      "wmo": 51,
      "windKt": 6,
      "windDir": 150
    },
    "Ensenada": {
      "tempF": 66,
      "tempC": 18.8,
      "condition": "Partly Cloudy",
      "wmo": 2,
      "windKt": 4,
      "windDir": 264
    },
    "Cabo San Lucas": {
      "tempF": 79,
      "tempC": 26.1,
      "condition": "Sunny",
      "wmo": 0,
      "windKt": 8,
      "windDir": 273
    },
    "Mazatlan": {
      "tempF": 86,
      "tempC": 30.2,
      "condition": "Sunny",
      "wmo": 0,
      "windKt": 4,
      "windDir": 208
    },
    "Puerto Vallarta": {
      "tempF": 84,
      "tempC": 29.0,
      "condition": "Overcast",
      "wmo": 3,
      "windKt": 3,
      "windDir": 200
    },
    "Manzanillo": {
      "tempF": 86,
      "tempC": 30.2,
      "condition": "Overcast",
      "wmo": 3,
      "windKt": 4,
      "windDir": 231
    },
    "Huatulco": {
      "tempF": 88,
      "tempC": 30.9,
      "condition": "Drizzle",
      "wmo": 53,
      "windKt": 4,
      "windDir": 163
    }
  }
}