{
  "generated_at": "2026-06-22T21:11:08.520104+00:00",
  "ports": {
    "Miami": {
      "tempF": 89,
      "tempC": 31.9,
      "condition": "Thunderstorm",
      "wmo": 95,
      "windKt": 9,
      "windDir": 146
    },
    "Key West": {
      "tempF": 90,
      "tempC": 32.0,
      "condition": "Thunderstorm",
      "wmo": 95,
      "windKt": 7,
      "windDir": 116
    },
    "Nassau": {
      "tempF": 88,
      "tempC": 31.0,
      "condition": "Sunny",
      "wmo": 0,
      "windKt": 7,
      "windDir": 142
    },
    "Bimini": {
      "tempF": 86,
      "tempC": 29.8,
      "condition": "Thunderstorm",
      "wmo": 95,
      "windKt": 6,
      "windDir": 147
    },
    "Freeport": {
      "tempF": 89,
      "tempC": 31.5,
      "condition": "Thunderstorm",
      "wmo": 95,
      "windKt": 8,
      "windDir": 171
    },
    "Berry Islands": {
      "tempF": 85,
      "tempC": 29.2,
      "condition": "Thunderstorm",
      "wmo": 95,
      "windKt": 8,
      "windDir": 140
    },
    "San Juan": {
      "tempF": 83,
      "tempC": 28.1,
      "condition": "Sunny",
      "wmo": 0,
      "windKt": 16,
      "windDir": 75
    },
    "St. Thomas": {
      "tempF": 82,
      "tempC": 28.0,
      "condition": "Partly Cloudy",
      "wmo": 2,
      "windKt": 17,
      "windDir": 81
    },
    "St. Croix": {
      "tempF": 84,
      "tempC": 29.0,
      "condition": "Partly Cloudy",
      "wmo": 2,
      "windKt": 15,
      "windDir": 78
    },
    "St. Kitts": {
      "tempF": 83,
      "tempC": 28.4,
      "condition": "Mostly Clear",
      "wmo": 1,
      "windKt": 15,
      "windDir": 82
    },
    "Antigua": {
      "tempF": 83,
      "tempC": 28.6,
      "condition": "Mostly Clear",
      "wmo": 1,
      "windKt": 16,
      "windDir": 79
    },
    "Barbados": {
      "tempF": 83,
      "tempC": 28.1,
      "condition": "Overcast",
      "wmo": 3,
      "windKt": 14,
      "windDir": 66
    },
    "St. Lucia": {
      "tempF": 78,
      "tempC": 25.5,
      "condition": "Light Drizzle",
      "wmo": 51,
      "windKt": 10,
      "windDir": 64
    },
    "Martinique": {
      "tempF": 80,
      "tempC": 26.6,
      "condition": "Overcast",
      "wmo": 3,
      "windKt": 14,
      "windDir": 58
    },
    "St. Maarten": {
      "tempF": 81,
      "tempC": 27.3,
      "condition": "Overcast",
      "wmo": 3,
      "windKt": 19,
      "windDir": 75
    },
    "Turks & Caicos": {
      "tempF": 83,
      "tempC": 28.5,
      "condition": "Thunderstorm",
      "wmo": 95,
      "windKt": 18,
      "windDir": 105
    },
    "Cozumel": {
      "tempF": 87,
      "tempC": 30.4,
      "condition": "Overcast",
      "wmo": 3,
      "windKt": 9,
      "windDir": 89
    },
    "Costa Maya": {
      "tempF": 86,
      "tempC": 30.0,
      "condition": "Overcast",
      "wmo": 3,
      "windKt": 11,
      "windDir": 87
    },
    "Roatan": {
      "tempF": 81,
      "tempC": 27.4,
      "condition": "Mostly Clear",
      "wmo": 1,
      "windKt": 19,
      "windDir": 80
    },
    "Belize City": {
      "tempF": 87,
      "tempC": 30.6,
      "condition": "Light Drizzle",
      "wmo": 51,
      "windKt": 12,
      "windDir": 96
    },
    "Grand Cayman": {
      "tempF": 88,
      "tempC": 31.2,
      "condition": "Thunderstorm",
      "wmo": 95,
      "windKt": 11,
      "windDir": 76
    },
    "Ocho Rios": {
      "tempF": 86,
      "tempC": 30.2,
      "condition": "Light Drizzle",
      "wmo": 51,
      "windKt": 10,
      "windDir": 94
    },
    "Aruba": {
      "tempF": 83,
      "tempC": 28.6,
      "condition": "Sunny",
      "wmo": 0,
      "windKt": 22,
      "windDir": 87
    },
    "Curacao": {
      "tempF": 86,
      "tempC": 29.8,
      "condition": "Mostly Clear",
      "wmo": 1,
      "windKt": 18,
      "windDir": 90
    },
    "Cartagena": {
      "tempF": 90,
      "tempC": 32.3,
      "condition": "Sunny",
      "wmo": 0,
      "windKt": 9,
      "windDir": 357
    },
    "Barcelona": {
      "tempF": 80,
      "tempC": 26.6,
      "condition": "Partly Cloudy",
      "wmo": 2,
      "windKt": 1,
      "windDir": 166
    },
    "Valencia": {
      "tempF": 81,
      "tempC": 27.0,
      "condition": "Sunny",
      "wmo": 0,
      "windKt": 0,
      "windDir": 270
    },
    "Palma": {
      "tempF": 82,
      "tempC": 27.6,
      "condition": "Mostly Clear",
      "wmo": 1,
      "windKt": 1,
      "windDir": 352
    },
    "Ibiza": {
      "tempF": 78,
      "tempC": 25.4,
      "condition": "Sunny",
      "wmo": 0,
      "windKt": 2,
      "windDir": 49
    },
    "Malaga": {
      "tempF": 79,
      "tempC": 25.9,
      "condition": "Overcast",
      "wmo": 3,
      "windKt": 1,
      "windDir": 143
    },
    "Cadiz": {
      "tempF": 72,
      "tempC": 22.4,
      "condition": "Overcast",
      "wmo": 3,
      "windKt": 2,
      "windDir": 304
    },
    "Lisbon": {
      "tempF": 70,
      "tempC": 21.3,
      "condition": "Overcast",
      "wmo": 3,
      "windKt": 7,
      "windDir": 342
    },
    "Marseille": {
      "tempF": 81,
      "tempC": 27.2,
      "condition": "Overcast",
      "wmo": 3,
      "windKt": 4,
      "windDir": 290
    },
    "Nice": {
      "tempF": 81,
      "tempC": 27.2,
      "condition": "Sunny",
      "wmo": 0,
      "windKt": 4,
      "windDir": 348
    },
    "Monaco": {
      "tempF": 84,
      "tempC": 28.7,
      "condition": "Sunny",
      "wmo": 0,
      "windKt": 4,
      "windDir": 333
    },
    "Genoa": {
      "tempF": 78,
      "tempC": 25.8,
      "condition": "Partly Cloudy",
      "wmo": 2,
      "windKt": 5,
      "windDir": 21
    },
    "La Spezia": {
      "tempF": 82,
      "tempC": 27.9,
      "condition": "Overcast",
      "wmo": 3,
      "windKt": 4,
      "windDir": 306
    },
    "Livorno": {
      "tempF": 80,
      "tempC": 26.9,
      "condition": "Sunny",
      "wmo": 0,
      "windKt": 2,
      "windDir": 63
    },
    "Civitavecchia": {
      "tempF": 79,
      "tempC": 26.2,
      "condition": "Partly Cloudy",
      "wmo": 2,
      "windKt": 3,
      "windDir": 74
    },
    "Naples": {
      "tempF": 80,
      "tempC": 26.8,
      "condition": "Sunny",
      "wmo": 0,
      "windKt": 2,
      "windDir": 333
    },
    "Sardinia": {
      "tempF": 78,
      "tempC": 25.8,
      "condition": "Sunny",
      "wmo": 0,
      "windKt": 1,
      "windDir": 101
    },
    "Corsica": {
      "tempF": 68,
      "tempC": 20.0,
      "condition": "Sunny",
      "wmo": 0,
      "windKt": 5,
      "windDir": 62
    },
    "Split": {
      "tempF": 86,
      "tempC": 29.9,
      "condition": "Sunny",
      "wmo": 0,
      "windKt": 3,
      "windDir": 16
    },
    "Dubrovnik": {
      "tempF": 82,
      "tempC": 28.0,
      "condition": "Mostly Clear",
      "wmo": 1,
      "windKt": 4,
      "windDir": 35
    },
    "Venice": {
      "tempF": 76,
      "tempC": 24.7,
      "condition": "Overcast",
      "wmo": 3,
      "windKt": 13,
      "windDir": 343
    },
    "Athens": {
      "tempF": 78,
      "tempC": 25.7,
      "condition": "Sunny",
      "wmo": 0,
      "windKt": 1,
      "windDir": 329
    },
    "Santorini": {
      "tempF": 74,
      "tempC": 23.6,
      "condition": "Sunny",
      "wmo": 0,
      "windKt": 6,
      "windDir": 320
    },
    "Mykonos": {
      "tempF": 74,
      "tempC": 23.4,
      "condition": "Sunny",
      "wmo": 0,
      "windKt": 13,
      "windDir": 356
    },
    "Rhodes": {
      "tempF": 80,
      "tempC": 26.6,
      "condition": "Sunny",
      "wmo": 0,
      "windKt": 7,
      "windDir": 283
    },
    "Corfu": {
      "tempF": 78,
      "tempC": 25.8,
      "condition": "Mostly Clear",
      "wmo": 1,
      "windKt": 1,
      "windDir": 243
    },
    "Istanbul": {
      "tempF": 71,
      "tempC": 21.4,
      "condition": "Partly Cloudy",
      "wmo": 2,
      "windKt": 7,
      "windDir": 43
    },
    "Izmir": {
      "tempF": 79,
      "tempC": 26.3,
      "condition": "Sunny",
      "wmo": 0,
      "windKt": 2,
      "windDir": 51
    },
    "Cyprus": {
      "tempF": 81,
      "tempC": 27.0,
      "condition": "Mostly Clear",
      "wmo": 1,
      "windKt": 3,
      "windDir": 257
    },
    "Haifa": {
      "tempF": 77,
      "tempC": 24.8,
      "condition": "Mostly Clear",
      "wmo": 1,
      "windKt": 3,
      "windDir": 260
    },
    "Alexandria": {
      "tempF": 76,
      "tempC": 24.3,
      "condition": "Mostly Clear",
      "wmo": 1,
      "windKt": 5,
      "windDir": 304
    },
    "Bonaire": {
      "tempF": 84,
      "tempC": 28.7,
      "condition": "Mostly Clear",
      "wmo": 1,
      "windKt": 19,
      "windDir": 86
    },
    "Dominica": {
      "tempF": 81,
      "tempC": 27.4,
      "condition": "Overcast",
      "wmo": 3,
      "windKt": 16,
      "windDir": 72
    },
    "Falmouth": {
      "tempF": 89,
      "tempC": 31.7,
      "condition": "Sunny",
      "wmo": 0,
      "windKt": 8,
      "windDir": 74
    },
    "La Romana": {
      "tempF": 87,
      "tempC": 30.4,
      "condition": "Mostly Clear",
      "wmo": 1,
      "windKt": 9,
      "windDir": 69
    },
    "Puerto Plata": {
      "tempF": 86,
      "tempC": 30.0,
      "condition": "Thunderstorm",
      "wmo": 95,
      "windKt": 14,
      "windDir": 82
    },
    "Samana": {
      "tempF": 83,
      "tempC": 28.3,
      "condition": "Partly Cloudy",
      "wmo": 2,
      "windKt": 10,
      "windDir": 83
    },
    "Santo Domingo": {
      "tempF": 87,
      "tempC": 30.7,
      "condition": "Mostly Clear",
      "wmo": 1,
      "windKt": 4,
      "windDir": 137
    },
    "Ensenada": {
      "tempF": 69,
      "tempC": 20.8,
      "condition": "Mostly Clear",
      "wmo": 1,
      "windKt": 8,
      "windDir": 261
    },
    "Cabo San Lucas": {
      "tempF": 89,
      "tempC": 31.6,
      "condition": "Sunny",
      "wmo": 0,
      "windKt": 8,
      "windDir": 137
    },
    "Mazatlan": {
      "tempF": 89,
      "tempC": 31.9,
      "condition": "Overcast",
      "wmo": 3,
      "windKt": 6,
      "windDir": 248
    },
    "Puerto Vallarta": {
      "tempF": 84,
      "tempC": 29.0,
      "condition": "Partly Cloudy",
      "wmo": 2,
      "windKt": 8,
      "windDir": 187
    },
    "Manzanillo": {
      "tempF": 88,
      "tempC": 31.0,
      "condition": "Mostly Clear",
      "wmo": 1,
      "windKt": 5,
      "windDir": 189
    },
    "Huatulco": {
      "tempF": 91,
      "tempC": 32.9,
      "condition": "Mostly Clear",
      "wmo": 1,
      "windKt": 7,
      "windDir": 117
    }
  }
}