{
  "generated_at": "2026-05-16T10:35:08.686890+00:00",
  "ports": {
    "Miami": {
      "tempF": 71,
      "tempC": 21.8,
      "condition": "Sunny",
      "wmo": 0,
      "windKt": 4,
      "windDir": 328
    },
    "Key West": {
      "tempF": 77,
      "tempC": 25.2,
      "condition": "Mostly Clear",
      "wmo": 1,
      "windKt": 5,
      "windDir": 74
    },
    "Nassau": {
      "tempF": 74,
      "tempC": 23.3,
      "condition": "Mostly Clear",
      "wmo": 1,
      "windKt": 4,
      "windDir": 68
    },
    "Bimini": {
      "tempF": 78,
      "tempC": 25.6,
      "condition": "Sunny",
      "wmo": 0,
      "windKt": 18,
      "windDir": 126
    },
    "Freeport": {
      "tempF": 71,
      "tempC": 21.9,
      "condition": "Sunny",
      "wmo": 0,
      "windKt": 4,
      "windDir": 80
    },
    "Berry Islands": {
      "tempF": 79,
      "tempC": 26.1,
      "condition": "Sunny",
      "wmo": 0,
      "windKt": 13,
      "windDir": 62
    },
    "San Juan": {
      "tempF": 77,
      "tempC": 25.1,
      "condition": "Partly Cloudy",
      "wmo": 2,
      "windKt": 7,
      "windDir": 123
    },
    "St. Thomas": {
      "tempF": 81,
      "tempC": 27.4,
      "condition": "Mostly Clear",
      "wmo": 1,
      "windKt": 16,
      "windDir": 105
    },
    "St. Croix": {
      "tempF": 77,
      "tempC": 25.0,
      "condition": "Light Drizzle",
      "wmo": 51,
      "windKt": 11,
      "windDir": 98
    },
    "St. Kitts": {
      "tempF": 80,
      "tempC": 26.5,
      "condition": "Sunny",
      "wmo": 0,
      "windKt": 11,
      "windDir": 93
    },
    "Antigua": {
      "tempF": 80,
      "tempC": 26.5,
      "condition": "Light Drizzle",
      "wmo": 51,
      "windKt": 13,
      "windDir": 96
    },
    "Barbados": {
      "tempF": 80,
      "tempC": 26.6,
      "condition": "Sunny",
      "wmo": 0,
      "windKt": 12,
      "windDir": 91
    },
    "St. Lucia": {
      "tempF": 75,
      "tempC": 23.8,
      "condition": "Light Drizzle",
      "wmo": 51,
      "windKt": 8,
      "windDir": 103
    },
    "Martinique": {
      "tempF": 76,
      "tempC": 24.5,
      "condition": "Mostly Clear",
      "wmo": 1,
      "windKt": 8,
      "windDir": 95
    },
    "St. Maarten": {
      "tempF": 80,
      "tempC": 26.4,
      "condition": "Sunny",
      "wmo": 0,
      "windKt": 15,
      "windDir": 100
    },
    "Turks & Caicos": {
      "tempF": 81,
      "tempC": 27.2,
      "condition": "Partly Cloudy",
      "wmo": 2,
      "windKt": 12,
      "windDir": 103
    },
    "Cozumel": {
      "tempF": 80,
      "tempC": 26.8,
      "condition": "Sunny",
      "wmo": 0,
      "windKt": 6,
      "windDir": 122
    },
    "Costa Maya": {
      "tempF": 82,
      "tempC": 27.5,
      "condition": "Sunny",
      "wmo": 0,
      "windKt": 8,
      "windDir": 114
    },
    "Roatan": {
      "tempF": 82,
      "tempC": 27.6,
      "condition": "Sunny",
      "wmo": 0,
      "windKt": 16,
      "windDir": 94
    },
    "Belize City": {
      "tempF": 74,
      "tempC": 23.5,
      "condition": "Sunny",
      "wmo": 0,
      "windKt": 3,
      "windDir": 90
    },
    "Grand Cayman": {
      "tempF": 82,
      "tempC": 27.7,
      "condition": "Sunny",
      "wmo": 0,
      "windKt": 10,
      "windDir": 79
    },
    "Ocho Rios": {
      "tempF": 78,
      "tempC": 25.5,
      "condition": "Mostly Clear",
      "wmo": 1,
      "windKt": 5,
      "windDir": 108
    },
    "Aruba": {
      "tempF": 81,
      "tempC": 27.4,
      "condition": "Partly Cloudy",
      "wmo": 2,
      "windKt": 19,
      "windDir": 93
    },
    "Curacao": {
      "tempF": 80,
      "tempC": 26.9,
      "condition": "Sunny",
      "wmo": 0,
      "windKt": 13,
      "windDir": 94
    },
    "Cartagena": {
      "tempF": 81,
      "tempC": 27.4,
      "condition": "Mostly Clear",
      "wmo": 1,
      "windKt": 2,
      "windDir": 71
    },
    "Barcelona": {
      "tempF": 64,
      "tempC": 17.9,
      "condition": "Mostly Clear",
      "wmo": 1,
      "windKt": 4,
      "windDir": 115
    },
    "Valencia": {
      "tempF": 68,
      "tempC": 19.9,
      "condition": "Sunny",
      "wmo": 0,
      "windKt": 2,
      "windDir": 261
    },
    "Palma": {
      "tempF": 63,
      "tempC": 17.3,
      "condition": "Sunny",
      "wmo": 0,
      "windKt": 11,
      "windDir": 317
    },
    "Ibiza": {
      "tempF": 66,
      "tempC": 18.9,
      "condition": "Mostly Clear",
      "wmo": 1,
      "windKt": 9,
      "windDir": 288
    },
    "Malaga": {
      "tempF": 72,
      "tempC": 22.3,
      "condition": "Partly Cloudy",
      "wmo": 2,
      "windKt": 6,
      "windDir": 189
    },
    "Cadiz": {
      "tempF": 65,
      "tempC": 18.2,
      "condition": "Mostly Clear",
      "wmo": 1,
      "windKt": 8,
      "windDir": 181
    },
    "Lisbon": {
      "tempF": 65,
      "tempC": 18.6,
      "condition": "Mostly Clear",
      "wmo": 1,
      "windKt": 8,
      "windDir": 1
    },
    "Marseille": {
      "tempF": 61,
      "tempC": 16.2,
      "condition": "Sunny",
      "wmo": 0,
      "windKt": 17,
      "windDir": 316
    },
    "Nice": {
      "tempF": 69,
      "tempC": 20.3,
      "condition": "Sunny",
      "wmo": 0,
      "windKt": 6,
      "windDir": 171
    },
    "Monaco": {
      "tempF": 64,
      "tempC": 17.7,
      "condition": "Sunny",
      "wmo": 0,
      "windKt": 5,
      "windDir": 165
    },
    "Genoa": {
      "tempF": 66,
      "tempC": 19.1,
      "condition": "Sunny",
      "wmo": 0,
      "windKt": 7,
      "windDir": 346
    },
    "La Spezia": {
      "tempF": 66,
      "tempC": 18.7,
      "condition": "Partly Cloudy",
      "wmo": 2,
      "windKt": 7,
      "windDir": 346
    },
    "Livorno": {
      "tempF": 60,
      "tempC": 15.8,
      "condition": "Overcast",
      "wmo": 3,
      "windKt": 8,
      "windDir": 302
    },
    "Civitavecchia": {
      "tempF": 60,
      "tempC": 15.8,
      "condition": "Partly Cloudy",
      "wmo": 2,
      "windKt": 13,
      "windDir": 301
    },
    "Naples": {
      "tempF": 65,
      "tempC": 18.5,
      "condition": "Partly Cloudy",
      "wmo": 2,
      "windKt": 15,
      "windDir": 266
    },
    "Sardinia": {
      "tempF": 67,
      "tempC": 19.4,
      "condition": "Mostly Clear",
      "wmo": 1,
      "windKt": 16,
      "windDir": 301
    },
    "Corsica": {
      "tempF": 43,
      "tempC": 6.0,
      "condition": "Partly Cloudy",
      "wmo": 2,
      "windKt": 7,
      "windDir": 290
    },
    "Split": {
      "tempF": 57,
      "tempC": 13.7,
      "condition": "Light Rain",
      "wmo": 61,
      "windKt": 14,
      "windDir": 302
    },
    "Dubrovnik": {
      "tempF": 61,
      "tempC": 16.0,
      "condition": "Thunderstorm",
      "wmo": 95,
      "windKt": 13,
      "windDir": 191
    },
    "Venice": {
      "tempF": 57,
      "tempC": 13.9,
      "condition": "Light Rain",
      "wmo": 61,
      "windKt": 5,
      "windDir": 318
    },
    "Athens": {
      "tempF": 76,
      "tempC": 24.4,
      "condition": "Overcast",
      "wmo": 3,
      "windKt": 7,
      "windDir": 209
    },
    "Santorini": {
      "tempF": 71,
      "tempC": 21.6,
      "condition": "Overcast",
      "wmo": 3,
      "windKt": 7,
      "windDir": 224
    },
    "Mykonos": {
      "tempF": 72,
      "tempC": 22.1,
      "condition": "Overcast",
      "wmo": 3,
      "windKt": 9,
      "windDir": 207
    },
    "Rhodes": {
      "tempF": 76,
      "tempC": 24.6,
      "condition": "Mostly Clear",
      "wmo": 1,
      "windKt": 2,
      "windDir": 270
    },
    "Corfu": {
      "tempF": 67,
      "tempC": 19.6,
      "condition": "Thunderstorm",
      "wmo": 95,
      "windKt": 11,
      "windDir": 205
    },
    "Istanbul": {
      "tempF": 72,
      "tempC": 22.3,
      "condition": "Sunny",
      "wmo": 0,
      "windKt": 6,
      "windDir": 203
    },
    "Izmir": {
      "tempF": 82,
      "tempC": 27.5,
      "condition": "Mostly Clear",
      "wmo": 1,
      "windKt": 9,
      "windDir": 186
    },
    "Cyprus": {
      "tempF": 81,
      "tempC": 27.1,
      "condition": "Sunny",
      "wmo": 0,
      "windKt": 10,
      "windDir": 195
    },
    "Haifa": {
      "tempF": 73,
      "tempC": 22.7,
      "condition": "Partly Cloudy",
      "wmo": 2,
      "windKt": 13,
      "windDir": 253
    },
    "Alexandria": {
      "tempF": 76,
      "tempC": 24.6,
      "condition": "Mostly Clear",
      "wmo": 1,
      "windKt": 5,
      "windDir": 297
    },
    "Bonaire": {
      "tempF": 80,
      "tempC": 26.8,
      "condition": "Sunny",
      "wmo": 0,
      "windKt": 15,
      "windDir": 88
    },
    "Dominica": {
      "tempF": 76,
      "tempC": 24.7,
      "condition": "Partly Cloudy",
      "wmo": 2,
      "windKt": 12,
      "windDir": 90
    },
    "Falmouth": {
      "tempF": 76,
      "tempC": 24.7,
      "condition": "Sunny",
      "wmo": 0,
      "windKt": 6,
      "windDir": 116
    },
    "La Romana": {
      "tempF": 75,
      "tempC": 24.0,
      "condition": "Partly Cloudy",
      "wmo": 2,
      "windKt": 4,
      "windDir": 91
    },
    "Puerto Plata": {
      "tempF": 76,
      "tempC": 24.7,
      "condition": "Overcast",
      "wmo": 3,
      "windKt": 5,
      "windDir": 132
    },
    "Samana": {
      "tempF": 76,
      "tempC": 24.2,
      "condition": "Overcast",
      "wmo": 3,
      "windKt": 4,
      "windDir": 67
    },
    "Santo Domingo": {
      "tempF": 74,
      "tempC": 23.4,
      "condition": "Mostly Clear",
      "wmo": 1,
      "windKt": 0,
      "windDir": 304
    },
    "Ensenada": {
      "tempF": 60,
      "tempC": 15.5,
      "condition": "Overcast",
      "wmo": 3,
      "windKt": 4,
      "windDir": 273
    },
    "Cabo San Lucas": {
      "tempF": 84,
      "tempC": 28.8,
      "condition": "Overcast",
      "wmo": 3,
      "windKt": 4,
      "windDir": 322
    },
    "Mazatlan": {
      "tempF": 76,
      "tempC": 24.3,
      "condition": "Partly Cloudy",
      "wmo": 2,
      "windKt": 4,
      "windDir": 107
    },
    "Puerto Vallarta": {
      "tempF": 70,
      "tempC": 20.9,
      "condition": "Overcast",
      "wmo": 3,
      "windKt": 3,
      "windDir": 27
    },
    "Manzanillo": {
      "tempF": 78,
      "tempC": 25.3,
      "condition": "Sunny",
      "wmo": 0,
      "windKt": 3,
      "windDir": 84
    },
    "Huatulco": {
      "tempF": 79,
      "tempC": 26.2,
      "condition": "Sunny",
      "wmo": 0,
      "windKt": 2,
      "windDir": 347
    }
  }
}